sasavg/SasViewRunner.py
sasavg/__init__.py
sasavg/sas/__init__.py
sasavg/sas/cli.py
sasavg/sas/qtgui/__init__.py
sasavg/sas/qtgui/convertUI.py
sasavg/sas/qtgui/Calculators/DataOperationUtilityPanel.py
sasavg/sas/qtgui/Calculators/DensityPanel.py
sasavg/sas/qtgui/Calculators/GenericScatteringCalculator.py
sasavg/sas/qtgui/Calculators/KiessigPanel.py
sasavg/sas/qtgui/Calculators/ResolutionCalculatorPanel.py
sasavg/sas/qtgui/Calculators/SldPanel.py
sasavg/sas/qtgui/Calculators/SlitSizeCalculator.py
sasavg/sas/qtgui/Calculators/__init__.py
sasavg/sas/qtgui/Calculators/UI/__init__.py
sasavg/sas/qtgui/Calculators/UnitTesting/DataOperationUtilityTest.py
sasavg/sas/qtgui/Calculators/UnitTesting/DensityCalculatorTest.py
sasavg/sas/qtgui/Calculators/UnitTesting/GenericScatteringCalculatorTest.py
sasavg/sas/qtgui/Calculators/UnitTesting/KiessigCalculatorTest.py
sasavg/sas/qtgui/Calculators/UnitTesting/ResolutionCalculatorPanelTest.py
sasavg/sas/qtgui/Calculators/UnitTesting/SLDCalculatorTest.py
sasavg/sas/qtgui/Calculators/UnitTesting/SlitSizeCalculatorTest.py
sasavg/sas/qtgui/Calculators/UnitTesting/__init__.py
sasavg/sas/qtgui/GL/__init__.py
sasavg/sas/qtgui/GL/color.py
sasavg/sas/qtgui/GL/cone.py
sasavg/sas/qtgui/GL/cube.py
sasavg/sas/qtgui/GL/cylinder.py
sasavg/sas/qtgui/GL/icosahedron.py
sasavg/sas/qtgui/GL/models.py
sasavg/sas/qtgui/GL/renderable.py
sasavg/sas/qtgui/GL/scene.py
sasavg/sas/qtgui/GL/sphere.py
sasavg/sas/qtgui/GL/surface.py
sasavg/sas/qtgui/GL/transforms.py
sasavg/sas/qtgui/GL/visual_checks/primitive_library.py
sasavg/sas/qtgui/GL/visual_checks/transform_library.py
sasavg/sas/qtgui/MainWindow/Acknowledgements.py
sasavg/sas/qtgui/MainWindow/CategoryManager.py
sasavg/sas/qtgui/MainWindow/DataExplorer.py
sasavg/sas/qtgui/MainWindow/DataManager.py
sasavg/sas/qtgui/MainWindow/DataState.py
sasavg/sas/qtgui/MainWindow/DroppableDataLoadWidget.py
sasavg/sas/qtgui/MainWindow/GuiManager.py
sasavg/sas/qtgui/MainWindow/MainWindow.py
sasavg-0.1.2.dist-info/METADATA
sasavg-0.1.2.dist-info/WHEEL
sasavg-0.1.2.dist-info/top_level.txt
sasavg-0.1.2.dist-info/RECORD
