Metadata-Version: 2.1
Name: sasavg
Version: 0.1.2
Summary: rotational averaging of SasView scattering data
Author: Alec Sabol-Pulling
License: Public Domain
Project-URL: Homepage, https://github.com/Sergey-ASP/SASAvg
Classifier: Natural Language :: English
Classifier: Operating System :: POSIX
Classifier: Operating System :: Microsoft :: Windows
Classifier: Programming Language :: Python :: 3.10
Requires-Python: >=3.10
Requires-Dist: sasdata
Requires-Dist: sasmodels
Requires-Dist: matplotlib>=3.9
Requires-Dist: periodictable
